hydra_plugins/wrangl_searchpath_plugin/__init__.py
hydra_plugins/wrangl_searchpath_plugin/wrangl_searchpath_plugin.py
wrangl/__init__.py
wrangl/conf/__init__.py
wrangl/conf/wrangl_experiment.yaml
wrangl/conf/wrangl_supervised_experiment.yaml
wrangl/conf/hydra/launcher/local.yaml
wrangl/conf/hydra/launcher/slurm.yaml
wrangl/examples/__init__.py
wrangl/examples/learn/__init__.py
wrangl/examples/learn/dynasent_clf/__init__.py
wrangl/examples/learn/dynasent_clf/train.py
wrangl/examples/learn/dynasent_clf/conf/default.yaml
wrangl/examples/learn/xor_clf/__init__.py
wrangl/examples/learn/xor_clf/train.py
wrangl/examples/learn/xor_clf/conf/default.yaml
wrangl/examples/learn/xor_clf/saves/wrangl-examples-xor_clf/mymodel-default/config.yaml
wrangl/examples/learn/xor_clf/saves/wrangl-examples-xor_clf/mymodel-default/.hydra/config.yaml
wrangl/examples/learn/xor_clf/saves/wrangl-examples-xor_clf/mymodel-default/.hydra/hydra.yaml
wrangl/examples/learn/xor_clf/saves/wrangl-examples-xor_clf/mymodel-default/.hydra/overrides.yaml
wrangl/examples/learn/xor_clf/saves/wrangl-examples-xor_clf/mymodel-default/logs/version_0/hparams.yaml
wrangl/examples/learn/xor_clf/saves/wrangl-examples-xor_clf/mymodel-default/logs/version_1/hparams.yaml
wrangl/examples/learn/xor_clf/saves/wrangl-examples-xor_clf/mymodel-default/logs/version_2/hparams.yaml
wrangl/examples/learn/xor_clf/saves/wrangl-examples-xor_clf/mymodel-default/logs/version_3/hparams.yaml
wrangl/examples/learn/xor_clf/saves/wrangl-examples-xor_clf/mymodel-default/logs/version_4/hparams.yaml
wrangl/examples/learn/xor_clf/saves/wrangl-examples-xor_clf/mymodel-default/logs/version_5/hparams.yaml
wrangl/examples/learn/xor_clf/saves/wrangl-examples-xor_clf/mymodel-default/logs/version_6/hparams.yaml
wrangl/interactive/__init__.py
wrangl/interactive/cmd.py
wrangl/interactive/docs.py
wrangl/interactive/plotter.py
wrangl/interactive/projects.py
wrangl/learn/__init__.py
wrangl/learn/callbacks.py
wrangl/learn/metrics.py
wrangl/learn/model.py
wrangl-0.0.10.dist-info/LICENSE
wrangl-0.0.10.dist-info/METADATA
wrangl-0.0.10.dist-info/WHEEL
wrangl-0.0.10.dist-info/entry_points.txt
wrangl-0.0.10.dist-info/top_level.txt
wrangl-0.0.10.dist-info/RECORD
