Metadata-Version: 2.1
Name: wrangl
Version: 0.0.10
Summary: Parallel data preprocessing for NLP and ML.
Home-page: https://github.com/r2llab/wrangl
Author: Victor Zhong
Author-email: victor@victorzhong.com
License: Apache 2
Keywords: text nlp machine-learning
Classifier: Development Status :: 3 - Alpha
Classifier: Intended Audience :: Developers
Classifier: License :: OSI Approved :: MIT License
Classifier: Programming Language :: Python :: 3
Requires-Python: >3.7
License-File: LICENSE
Requires-Dist: ujson
Requires-Dist: plotille
Requires-Dist: pandas
Requires-Dist: pdoc
Requires-Dist: wandb
Requires-Dist: hydra-core
Requires-Dist: hydra-submitit-launcher
Requires-Dist: lightning
Requires-Dist: gitpython
Requires-Dist: seaborn
Provides-Extra: dev
Requires-Dist: check-manifest ; extra == 'dev'
Requires-Dist: pdoc ; extra == 'dev'
Requires-Dist: twine ; extra == 'dev'
Provides-Extra: test
Requires-Dist: coverage ; extra == 'test'
Requires-Dist: nose ; extra == 'test'
